[1,["9dVp0JdXRIsakAWXHL2CYC@6c48a"],["_textureSource"],["cc.SpriteFrame"],0,[{"name":"ore_copper","rect":{"x":25,"y":31,"width":77,"height":70},"offset":{"x":-0.5,"y":-2},"originalSize":{"width":128,"height":128},"rotated":false,"capInsets":[0,0,0,0],"vertices":{"rawPosition":[-38.5,-35,0,38.5,-35,0,-38.5,35,0,38.5,35,0],"indexes":[0,1,2,2,1,3],"uv":[25,97,102,97,25,27,102,27],"nuv":[0.1953125,0.2109375,0.796875,0.2109375,0.1953125,0.7578125,0.796875,0.7578125],"minPos":{"x":-38.5,"y":-35,"z":0},"maxPos":{"x":38.5,"y":35,"z":0}},"packable":true,"pixelsToUnit":100,"pivot":{"x":0.5,"y":0.5},"meshType":0}],[0],0,[0],[0],[0]]
